{"trial_id": "20", "hyperparameters": {"space": [{"class_name": "Float", "config": {"name": "noise", "default": 0.005, "conditions": [], "min_value": 0.005, "max_value": 0.02, "step": null, "sampling": "linear"}}, {"class_name": "Int", "config": {"name": "units_x1", "default": null, "conditions": [], "min_value": 64, "max_value": 256, "step": 32, "sampling": "linear"}}, {"class_name": "Choice", "config": {"name": "l2_x1", "default": 0.001, "conditions": [], "values": [0.001, 0.01, 0.1], "ordered": true}}, {"class_name": "Float", "config": {"name": "dropout_x1", "default": 0.2, "conditions": [], "min_value": 0.2, "max_value": 0.5, "step": null, "sampling": "linear"}}, {"class_name": "Int", "config": {"name": "units_x2", "default": null, "conditions": [], "min_value": 32, "max_value": 128, "step": 16, "sampling": "linear"}}, {"class_name": "Choice", "config": {"name": "l2_x2", "default": 0.001, "conditions": [], "values": [0.001, 0.01, 0.1], "ordered": true}}, {"class_name": "Float", "config": {"name": "dropout_x2", "default": 0.2, "conditions": [], "min_value": 0.2, "max_value": 0.5, "step": null, "sampling": "linear"}}, {"class_name": "Int", "config": {"name": "units_combined", "default": null, "conditions": [], "min_value": 16, "max_value": 64, "step": 16, "sampling": "linear"}}, {"class_name": "Choice", "config": {"name": "l2_combined", "default": 0.001, "conditions": [], "values": [0.001, 0.01, 0.1], "ordered": true}}, {"class_name": "Float", "config": {"name": "dropout_combined", "default": 0.2, "conditions": [], "min_value": 0.2, "max_value": 0.5, "step": null, "sampling": "linear"}}, {"class_name": "Float", "config": {"name": "learning_rate", "default": 1e-05, "conditions": [], "min_value": 1e-05, "max_value": 0.001, "step": null, "sampling": "log"}}, {"class_name": "Int", "config": {"name": "units_x3", "default": null, "conditions": [], "min_value": 32, "max_value": 128, "step": 16, "sampling": "linear"}}, {"class_name": "Choice", "config": {"name": "l2_x3", "default": 0.0001, "conditions": [], "values": [0.0001, 0.001, 0.01], "ordered": true}}, {"class_name": "Float", "config": {"name": "dropout_x3", "default": 0.1, "conditions": [], "min_value": 0.1, "max_value": 0.3, "step": null, "sampling": "linear"}}, {"class_name": "Int", "config": {"name": "units_components1", "default": null, "conditions": [], "min_value": 32, "max_value": 128, "step": 16, "sampling": "linear"}}, {"class_name": "Int", "config": {"name": "units_components2", "default": null, "conditions": [], "min_value": 16, "max_value": 64, "step": 16, "sampling": "linear"}}, {"class_name": "Int", "config": {"name": "units_types1", "default": null, "conditions": [], "min_value": 32, "max_value": 128, "step": 16, "sampling": "linear"}}, {"class_name": "Int", "config": {"name": "units_types2", "default": null, "conditions": [], "min_value": 16, "max_value": 64, "step": 16, "sampling": "linear"}}, {"class_name": "Int", "config": {"name": "units_cause1", "default": null, "conditions": [], "min_value": 32, "max_value": 128, "step": 16, "sampling": "linear"}}, {"class_name": "Int", "config": {"name": "units_cause2", "default": null, "conditions": [], "min_value": 16, "max_value": 64, "step": 16, "sampling": "linear"}}, {"class_name": "Float", "config": {"name": "gamma", "default": 2.0, "conditions": [], "min_value": 2.0, "max_value": 5.0, "step": null, "sampling": "linear"}}], "values": {"noise": 0.009907710681735606, "units_x1": 64, "l2_x1": 0.01, "dropout_x1": 0.3474891050714335, "units_x2": 32, "l2_x2": 0.1, "dropout_x2": 0.4258928412221715, "units_combined": 64, "l2_combined": 0.001, "dropout_combined": 0.47242141333322696, "learning_rate": 0.0008622212796753964, "units_x3": 32, "l2_x3": 0.0001, "dropout_x3": 0.1, "units_components1": 32, "units_components2": 16, "units_types1": 32, "units_types2": 16, "units_cause1": 32, "units_cause2": 16, "gamma": 2.0}}, "metrics": {"metrics": {"loss": {"direction": "min", "observations": [{"value": [0.15828046202659607], "step": 48}]}, "components_output_loss": {"direction": "min", "observations": [{"value": [0.03368529677391052], "step": 48}]}, "type_output_loss": {"direction": "min", "observations": [{"value": [0.046031855046749115], "step": 48}]}, "cause_output_loss": {"direction": "min", "observations": [{"value": [0.0757240280508995], "step": 48}]}, "components_output_accuracy": {"direction": "min", "observations": [{"value": [0.4038258492946625], "step": 48}]}, "components_output_auc": {"direction": "min", "observations": [{"value": [0.9159968495368958], "step": 48}]}, "components_output_recall": {"direction": "min", "observations": [{"value": [0.17659242451190948], "step": 48}]}, "components_output_precision": {"direction": "min", "observations": [{"value": [0.6535305380821228], "step": 48}]}, "type_output_accuracy": {"direction": "min", "observations": [{"value": [0.5271793007850647], "step": 48}]}, "type_output_auc_1": {"direction": "min", "observations": [{"value": [0.9183375835418701], "step": 48}]}, "type_output_recall_1": {"direction": "min", "observations": [{"value": [0.4658498167991638], "step": 48}]}, "type_output_precision_1": {"direction": "min", "observations": [{"value": [0.8067635893821716], "step": 48}]}, "cause_output_accuracy": {"direction": "min", "observations": [{"value": [0.22849655151367188], "step": 48}]}, "cause_output_auc_2": {"direction": "min", "observations": [{"value": [0.9240244030952454], "step": 48}]}, "cause_output_recall_2": {"direction": "min", "observations": [{"value": [0.6637046337127686], "step": 48}]}, "cause_output_precision_2": {"direction": "min", "observations": [{"value": [0.7862712740898132], "step": 48}]}, "val_loss": {"direction": "min", "observations": [{"value": [0.14925698935985565], "step": 48}]}, "val_components_output_loss": {"direction": "min", "observations": [{"value": [0.031774863600730896], "step": 48}]}, "val_type_output_loss": {"direction": "min", "observations": [{"value": [0.04330602288246155], "step": 48}]}, "val_cause_output_loss": {"direction": "min", "observations": [{"value": [0.07134783267974854], "step": 48}]}, "val_components_output_accuracy": {"direction": "min", "observations": [{"value": [0.4351969361305237], "step": 48}]}, "val_components_output_auc": {"direction": "min", "observations": [{"value": [0.9275132417678833], "step": 48}]}, "val_components_output_recall": {"direction": "min", "observations": [{"value": [0.22189263999462128], "step": 48}]}, "val_components_output_precision": {"direction": "min", "observations": [{"value": [0.6956366300582886], "step": 48}]}, "val_type_output_accuracy": {"direction": "min", "observations": [{"value": [0.5493170022964478], "step": 48}]}, "val_type_output_auc_1": {"direction": "min", "observations": [{"value": [0.9275087118148804], "step": 48}]}, "val_type_output_recall_1": {"direction": "min", "observations": [{"value": [0.4872158467769623], "step": 48}]}, "val_type_output_precision_1": {"direction": "min", "observations": [{"value": [0.8351502418518066], "step": 48}]}, "val_cause_output_accuracy": {"direction": "min", "observations": [{"value": [0.22760482132434845], "step": 48}]}, "val_cause_output_auc_2": {"direction": "min", "observations": [{"value": [0.9332295060157776], "step": 48}]}, "val_cause_output_recall_2": {"direction": "min", "observations": [{"value": [0.6811513304710388], "step": 48}]}, "val_cause_output_precision_2": {"direction": "min", "observations": [{"value": [0.793802797794342], "step": 48}]}, "lr": {"direction": "min", "observations": [{"value": [1.3472207683662418e-05], "step": 48}]}}}, "score": 0.14925698935985565, "best_step": 48, "status": "COMPLETED", "message": null}